pymopac/__init__.py
pymopac/helpers.py
pymopac/input.py
pymopac/output.py
pymopac-1.0.dist-info/LICENSE
pymopac-1.0.dist-info/METADATA
pymopac-1.0.dist-info/WHEEL
pymopac-1.0.dist-info/top_level.txt
pymopac-1.0.dist-info/RECORD
