Metadata-Version: 2.1
Name: pymopac
Version: 1.0
Summary: a python wrapper to interact with the semiempirical quantum chemistry program MOPAC
Author: Acetylsalicylsaeure
License: GNU GENERAL PUBLIC LICENSE
Project-URL: Repository, https://github.com/Acetylsalicylsaeure/pymopac
Project-URL: Documentation, https://pymopac.readthedocs.io
Keywords: MOPAC,wrapper,PM3,PM6,PM7,AM1,semiempirical,quantum
Classifier: Development Status :: 5 - Production/Stable
Classifier: Intended Audience :: Education
Classifier: Topic :: Scientific/Engineering :: Chemistry
Classifier: License :: OSI Approved :: GNU General Public License v3 (GPLv3)
Classifier: Programming Language :: Python :: 3.9
Classifier: Programming Language :: Python :: 3.10
Classifier: Programming Language :: Python :: 3.11
Classifier: Programming Language :: Python :: 3.12
License-File: LICENSE
Requires-Dist: rdkit
Requires-Dist: numpy
Requires-Dist: matplotlib
